Metadata-Version: 1.0
Name: mean-stdev-prob-n
Version: 10.0
Summary: Probability density function
Home-page: UNKNOWN
Author: Shamushideen Sule
Author-email: aneru.sule@gmail.com
License: UNKNOWN
Platform: UNKNOWN
